CHANGES.txt
MANIFEST.in
README.txt
development.ini
production.ini
setup.cfg
setup.py
prism_core/__init__.py
prism_core/controllers.py
prism_core/errors.py
prism_core/jsonerrors.py
prism_core/util.py
prism_core/views.py
prism_core.egg-info/PKG-INFO
prism_core.egg-info/SOURCES.txt
prism_core.egg-info/dependency_links.txt
prism_core.egg-info/entry_points.txt
prism_core.egg-info/not-zip-safe
prism_core.egg-info/requires.txt
prism_core.egg-info/top_level.txt