Metadata-Version: 1.1
Name: prism-core
Version: 0.0
Summary: prism_core
Home-page: https://github.com/elliotpeele/prism_core
Author: Elliot Peele
Author-email: elliot@bentlogic.net
License: UNKNOWN
Keywords: web wsgi bfg pylons pyramid
Platform: UNKNOWN
Classifier: Programming Language :: Python
Classifier: Framework :: Pyramid
Classifier: Topic :: Internet :: WWW/HTTP
Classifier: Topic :: Internet :: WWW/HTTP :: WSGI :: Application
